easy_yolo/__init__.py
easy_yolo/yolo-cam.py
easy_yolo/yolo_img.py
easy_yolo/yolo_vid.py
easy_yolo-0.0.2.dist-info/LICENSE
easy_yolo-0.0.2.dist-info/METADATA
easy_yolo-0.0.2.dist-info/WHEEL
easy_yolo-0.0.2.dist-info/top_level.txt
easy_yolo-0.0.2.dist-info/RECORD
