Metadata-Version: 2.1
Name: easy-yolo
Version: 0.0.2
Summary: Library to easily test YOLOv3 models
Home-page: https://github.com/pandeyarjun242
Author: Arjun Pandey
Author-email: apandey@jpischool.com
License: UNKNOWN
Platform: UNKNOWN
Classifier: Programming Language :: Python :: 3
Classifier: License :: OSI Approved :: MIT License
Classifier: Operating System :: OS Independent
Requires-Python: >=3.6
Requires-Dist: opencv-python
